README.md
setup.py
docums_nav_enhancements/__init__.py
docums_nav_enhancements.egg-info/PKG-INFO
docums_nav_enhancements.egg-info/SOURCES.txt
docums_nav_enhancements.egg-info/dependency_links.txt
docums_nav_enhancements.egg-info/entry_points.txt
docums_nav_enhancements.egg-info/not-zip-safe
docums_nav_enhancements.egg-info/requires.txt
docums_nav_enhancements.egg-info/top_level.txt