Metadata-Version: 2.1
Name: docums-nav-enhancements
Version: 0.9.1
Summary: This is a small plugin for the excellent Docums project which makes some enhancements to the navigation.
Home-page: https://github.com/khanhduy1407/docums-nav-enhancements
Author: NKDuy
Author-email: kn145660@gmail.com
License: MIT
Platform: UNKNOWN
Classifier: Programming Language :: Python :: 2
Classifier: Programming Language :: Python :: 3
Classifier: License :: OSI Approved :: MIT License
Classifier: Operating System :: OS Independent
Classifier: Intended Audience :: Developers
Classifier: Topic :: Documentation
